bin/__init__.py
bin/core_lib
core_lib/__init__.py
core_lib/core_lib.py
core_lib/core_lib_listener.py
core_lib/core_lib_main.py
core_lib/alembic/__init__.py
core_lib/alembic/alembic.py
core_lib/cache/__init__.py
core_lib/cache/cache_decorator.py
core_lib/cache/cache_handler.py
core_lib/cache/cache_handler_memcached.py
core_lib/cache/cache_handler_no_cache.py
core_lib/cache/cache_handler_ram.py
core_lib/cache/cache_handler_redis.py
core_lib/cache/cache_registry.py
core_lib/client/__init__.py
core_lib/client/client_base.py
core_lib/client/solr_client.py
core_lib/config/__init__.py
core_lib/config/core_lib.yaml
core_lib/connection/__init__.py
core_lib/connection/connection.py
core_lib/connection/connection_registry.py
core_lib/connection/elasticsearch_connection.py
core_lib/connection/elasticsearch_connection_registry.py
core_lib/connection/mongodb_connection.py
core_lib/connection/mongodb_connection_registry.py
core_lib/connection/neo4j_connection.py
core_lib/connection/neo4j_connection_registry.py
core_lib/connection/object_connection.py
core_lib/connection/object_connection_registry.py
core_lib/connection/solr_connection.py
core_lib/connection/solr_connection_registry.py
core_lib/connection/sql_alchemy_connection.py
core_lib/connection/sql_alchemy_connection_registry.py
core_lib/data_layers/__init__.py
core_lib/data_layers/data/__init__.py
core_lib/data_layers/data/data_helpers.py
core_lib/data_layers/data/db/__init__.py
core_lib/data_layers/data/db/migrations/__init__.py
core_lib/data_layers/data/db/migrations/versions/__init__.py
core_lib/data_layers/data/db/sqlalchemy/__init__.py
core_lib/data_layers/data/db/sqlalchemy/base.py
core_lib/data_layers/data/db/sqlalchemy/mixins/__init__.py
core_lib/data_layers/data/db/sqlalchemy/mixins/soft_delete_mixin.py
core_lib/data_layers/data/db/sqlalchemy/mixins/soft_delete_token_mixin.py
core_lib/data_layers/data/db/sqlalchemy/types/__init__.py
core_lib/data_layers/data/db/sqlalchemy/types/int_enum.py
core_lib-0.1.1.dist-info/licenses/LICENSE
core_lib-0.1.1.dist-info/METADATA
core_lib-0.1.1.dist-info/WHEEL
core_lib-0.1.1.dist-info/top_level.txt
core_lib-0.1.1.dist-info/RECORD
